Workbook

Sheet Raw financials
A1: Manchester United Financial Analysis
A3: Financial Metric (£m) | B3: 2021 | C3: 2022 | D3: 2023 | E3: 2024 | F3: 2025
A4: Revenue | B4: 494.1 | C4: 583.2 | D4: 648.4 | E4: 661.8 | F4: 666.5
A5: Commercial Revenue | B5: 232.2 | C5: 257.8 | D5: 302.9 | E5: 302.9 | F5: 333.3
A6: Broadcasting Revenue | B6: 254.8 | C6: 214.9 | D6: 209.1 | E6: 221.8 | F6: 172.9
A7: Matchday Revenue | B7: 7.1 | C7: 110.5 | D7: 136.4 | E7: 137.1 | F7: 160.3
A8: Operating Revenue
A9: Operating Profit / (Loss)
A10: Net Profit / (Loss)
A11: Cash and Cash equivalents
A12: Borrowings / Debt
A13: Revenue Growth % | C13: =(C4-B4)/B4 -> 0.18032787 | D13: =(D4-C4)/C4 -> 0.11179698 | E13: =(E4-D4)/D4 -> 0.020666255 | F13: =(F4-E4)/D4 -> 0.007248612
A14: Revenue Check | B14: =SUM(B5:B7)-B4 -> 0 | C14: =SUM(C5:C7)-C4 -> 0 | D14: =SUM(D5:D7)-D4 -> 0 | E14: =SUM(E5:E7)-E4 -> 0 | F14: =SUM(F5:F7)-F4 -> 0

Sheet Revenue analysis
A1: Manchester United Revenue Analysis
A3: Revenue Stream (£m) | B3: 2021 | C3: 2022 | D3: 2023 | E3: 2024 | F3: 2025
A4: Commercial | B4: ='Raw financials'!B5 -> 232.2 | C4: ='Raw financials'!C5 -> 257.8 | D4: ='Raw financials'!D5 -> 302.9 | E4: ='Raw financials'!E5 -> 302.9 | F4: ='Raw financials'!F5 -> 333.3
A5: Broadcasting | B5: ='Raw financials'!B6 -> 254.8 | C5: ='Raw financials'!C6 -> 214.9 | D5: ='Raw financials'!D6 -> 209.1 | E5: ='Raw financials'!E6 -> 221.8 | F5: ='Raw financials'!F6 -> 172.9
A6: Matchday | B6: ='Raw financials'!B7 -> 7.1 | C6: ='Raw financials'!C7 -> 110.5 | D6: ='Raw financials'!D7 -> 136.4 | E6: ='Raw financials'!E7 -> 137.1 | F6: ='Raw financials'!F7 -> 160.3
A7: Total Revenue | B7: ='Raw financials'!B4 -> 494.1 | C7: ='Raw financials'!C4 -> 583.2 | D7: ='Raw financials'!D4 -> 648.4 | E7: ='Raw financials'!E4 -> 661.8 | F7: ='Raw financials'!F4 -> 666.5
A9: 2025 Revenue Mix
A10: Commercial | B10: =F4/$F$7 -> 0.50007502
A11: Broadcasting | B11: =F5/$F$7 -> 0.25941485
A12: Matchday | B12: =F6/$F$7 -> 0.24051013

Sheet Profitability
A1: Manchester United Profitability Analysis
A3: Financial Metric (£m) | B3: 2021 | C3: 2022 | D3: 2023 | E3: 2024 | F3: 2025 | H3: Year | I3: Operating Profit | J3: Net Profit
A4: Revenue | B4: ='Raw financials'!B4 -> 494.1 | C4: ='Raw financials'!C4 -> 583.2 | D4: ='Raw financials'!D4 -> 648.4 | E4: ='Raw financials'!E4 -> 661.8 | F4: ='Raw financials'!F4 -> 666.5 | H4: 2021 | I4: -36.926 | J4: -92.216
A5: Operating Expenses | B5: 538.424 | C5: 692.52 | D5: 681.117 | E5: 768.53 | F5: 733.686 | H5: 2022 | I5: -87.384 | J5: -115.51
A6: Operating Profit / (Loss) | B6: -36.926 | C6: -87.384 | D6: -11.205 | E6: -69.267 | F6: -18.43 | H6: 2023 | I6: -11.205 | J6: -28.702
A7: Net Profit / (Loss) | B7: -92.216 | C7: -115.51 | D7: -28.702 | E7: -113.17 | F7: -33.023 | H7: 2024 | I7: -69.267 | J7: -113.17
A8: Operating Margin | B8: =B6/B4 -> -0.07473386 | C8: =C6/C4 -> -0.14983539 | D8: =D6/D4 -> -0.017280999 | E8: =E6/E4 -> -0.10466455 | F8: =F6/F4 -> -0.027651913 | H8: 2025 | I8: -18.43 | J8: -33.023
A9: Net Margin | B9: =B7/B4 -> -0.18663428 | C9: =C7/C4 -> -0.19806241 | D9: =D7/D4 -> -0.044265885 | E9: =E7/E4 -> -0.17100332 | F9: =F7/F4 -> -0.049546887

Sheet Balance sheet and debt
A1: Manchester United Balance Sheet and Debt Analysis
A3: Financial Metric (£m) | B3: 2021 | C3: 2022 | D3: 2023 | E3: 2024 | F3: 2025 | H3: Year | I3: Net Debt (£m)
A4: Cash and Cash Equivalents | B4: 110.658 | C4: 121.223 | D4: 76.019 | E4: 73.549 | F4: 86.1 | H4: 2021 | I4: 419.542
A5: Total Borrowings | B5: 530.2 | C5: 636.2 | D5: 613.3 | E5: 546.6 | F5: 637 | H5: 2022 | I5: 514.977
A6: Net Debt | B6: =B5-B4 -> 419.542 | C6: =C5-C4 -> 514.977 | D6: =D5-D4 -> 537.281 | E6: =E5-E4 -> 473.051 | F6: =F5-F4 -> 550.9 | H6: 2023 | I6: 537.281
A7: Total Assets | B7: 1260.31 | C7: 1293.665 | D7: 1317.944 | E7: 1344.787 | F7: 1637.733 | H7: 2024 | I7: 473.051
A8: Total liabilities | B8: 987.798 | C8: 1166.157 | D8: 1213.994 | E8: 1199.897 | F8: 1444 | H8: 2025 | I8: 550.9
A9: Net Assets / Equity | B9: 272.512 | C9: 127.508 | D9: 103.95 | E9: 144.89 | F9: 193.733
A10: Debt-to-Assets Ratio | B10: =B5/B7 -> 0.42069015 | C10: =C5/C7 -> 0.4917811 | D10: =D5/D7 -> 0.46534602 | E10: =E5/E7 -> 0.40645842 | F10: =F5/F7 -> 0.38895229

Sheet Dashboard
A1: Manchester United Financial Performance Dashboard
A2: Five-Year Financial Analysis | 2021-2025
A4: 2025 Revenue (£m) | C4: 2025 Net Profit / (Loss) (£m) | E4: 2025 Net Debt (£m) | G4: 2025 Debt-to-Assets
A5: £666.5m | C5: -£33.0m | E5: £550.9m | G5: 0.389
A36: Key Insights
A38: Revenue growth: Revenue increased from £494.1m in 2021 to £666.5m in 2025, an increase of approximately 35%.
A39: Profitability: Despite strong revenue recovery, Manchester United recorded a net loss in every year analysed. The 2025 net loss improved to £33.0m from £113.2m in 2024.
A40: Debt position: Net debt increased from £419.5m in 2021 to £550.9m in 2025. However, borrowings as a proportion of total assets fell to 38.9% in 2025, the lowest level across the five-year period.
A41: Overall: The five-year trend shows a business that has grown revenue significantly but has yet to convert that growth into consistent profitability, while maintaining a substantial debt burden.
